hatch_requirements_txt/__init__.py
hatch_requirements_txt/py.typed
hatch_requirements_txt-0.4.0.dist-info/METADATA
hatch_requirements_txt-0.4.0.dist-info/WHEEL
hatch_requirements_txt-0.4.0.dist-info/entry_points.txt
hatch_requirements_txt-0.4.0.dist-info/licenses/LICENSE
hatch_requirements_txt-0.4.0.dist-info/RECORD
