Metadata-Version: 2.1
Name: hatch-requirements-txt
Version: 0.4.0
Summary: Hatchling plugin to read project dependencies from requirements.txt
Project-URL: Homepage, https://github.com/repo-helper/hatch-requirements-txt
Project-URL: Issue Tracker, https://github.com/repo-helper/hatch-requirements-txt/issues
Project-URL: Source Code, https://github.com/repo-helper/hatch-requirements-txt
Author-email: Dominic Davis-Foster <dominic@davis-foster.co.uk>
License: Copyright (c) 2022 Dominic Davis-Foster
License-File: LICENSE
Keywords: dependencies,hatch,requirements
Classifier: Development Status :: 4 - Beta
Classifier: Framework :: Hatch
Classifier: Intended Audience :: Developers
Classifier: License :: OSI Approved :: MIT License
Classifier: Operating System :: OS Independent
Classifier: Programming Language :: Python
Classifier: Programming Language :: Python :: 3 :: Only
Classifier: Programming Language :: Python :: 3.6
Classifier: Programming Language :: Python :: 3.7
Classifier: Programming Language :: Python :: 3.8
Classifier: Programming Language :: Python :: 3.9
Classifier: Programming Language :: Python :: 3.10
Classifier: Programming Language :: Python :: 3.11
Classifier: Programming Language :: Python :: Implementation :: CPython
Classifier: Programming Language :: Python :: Implementation :: PyPy
Classifier: Topic :: Software Development :: Libraries :: Python Modules
Classifier: Topic :: System :: Archiving :: Packaging
Classifier: Typing :: Typed
Requires-Python: >=3.6.1
Requires-Dist: hatchling>=0.21.0
Requires-Dist: packaging>=21.3
